CalendarFusion/CalendarFusion.py
CalendarFusion/__init__.py
CalendarFusion-1.0.dist-info/LICENSE
CalendarFusion-1.0.dist-info/METADATA
CalendarFusion-1.0.dist-info/WHEEL
CalendarFusion-1.0.dist-info/top_level.txt
CalendarFusion-1.0.dist-info/RECORD
